uart_receiver-vitishls-files/uart_receiver.v
module uart_receiver (
    input wire uart_rx,
    input wire baud_rate_signal,
    input wire clk,
    input wire rst,
    output reg [7:0]data,
    output reg valid_data
);

parameter idle = 0, receive = 1;                //receiver state
reg [3:0]bit_counter = 0;                       //計算start-bit後收到幾個uart_rx，應該要可以收8-bit
reg state = idle;

reg [3:0]next_bit_counter = 0;
reg next_state = 0;
reg stop_bit;
reg valid_data_local;                           //標示數據是否接收完全。
reg [7:0]d = 0;                                     //data

always @(*) begin
    case (state)
        idle: begin                             //閒置狀態
            if (baud_rate_signal == 1) begin
                if (uart_rx == 0) begin         //接收到start-bit
                    next_state = receive;
                end else begin
                    next_state = state;
                end  
            end else begin
                next_state = idle;
            end
            valid_data_local = 0;               //不接收數據
            next_bit_counter = 0;               //重制bit-counter
        end
        receive: begin
            if (baud_rate_signal == 1) begin
                if (bit_counter == 4'd8) begin  //數到第八位了，所以這一位是stop-bit
                    stop_bit = uart_rx;
                    if (stop_bit == 1) begin    //正確停止位
                        valid_data_local = 1;   //資料接收完畢
                    end else begin
                        valid_data_local = 0;   //資料無效
                    end
                    next_bit_counter = 0;       //歸零
                    next_state = idle;
                end else begin                  //還沒數到第八位，可以接收資料
                    d[bit_counter] = uart_rx;
                    next_bit_counter = bit_counter + 1;
                    next_state = receive;
                    valid_data_local = 0;       //數據尚未接收完畢
                end
            end else begin
                next_bit_counter = bit_counter;
                next_state = receive;
                valid_data_local = 0;
            end
        end
    endcase
end


always @(posedge clk) begin
    if (rst) begin
        state <= idle;
        bit_counter <= 0;
        data <= 0;
        valid_data <= 0;
    end else begin
        state <= next_state;
        bit_counter <= next_bit_counter;
        data <= d;
        valid_data <= valid_data_local;
    end
end

    
endmodule

uart_receiver-vitishls-files/uart_receiver_tb.v
`include "uart_reciever.v"
`timescale  1ns / 1ps

module tb_uart_receiver;

// uart_receiver Parameters
parameter PERIOD = 10;
parameter idle  = 0;

//output of TX = input of RX
reg [9:0]in_data = {1'b1, 8'b01001011, 1'b0};

// uart_receiver Inputs
reg uart_rx = 0 ;
reg baud_rate_signal = 0 ;
reg clk = 0 ;
reg rst = 1 ;

// uart_receiver Outputs
wire  [7:0]  data                          ;
wire  valid_data                           ;

integer i;

initial
begin
    forever #(PERIOD/2)  clk=~clk;
end



uart_receiver #(
    .idle ( idle ))
 u_uart_receiver (
    .uart_rx(uart_rx),
    .baud_rate_signal( baud_rate_signal),
    .clk(clk),
    .rst(rst),
    .data(data[7:0]),
    .valid_data(valid_data)
);

initial begin
    $dumpfile("uart_receiver_tb.vcd");
    $dumpvars;
end

//system reset
initial
begin
    rst  =  1;
    #(PERIOD*5) 
    rst  =  0;
end


//buad_rate_signal
initial begin
    wait(rst == 1);
    wait(rst == 0);
    forever begin
        #(PERIOD)baud_rate_signal = ~baud_rate_signal; //
    end
end

initial begin
    wait(rst == 1);
    wait(rst == 0);
    for (i = 0; i < 10; i = i + 1) begin
        @(posedge baud_rate_signal) uart_rx = in_data[i];
    end

    if ({1'b1, data, 1'b0} == in_data) begin
        $display("correct");
    end else begin
        $display("wrong");
    end
    $finish;
end


endmodule

uart_receiver-vitishls-files/uart_receiver_tb.vcd
$date
	Wed Jan 08 17:26:02 2025
$end
$version
	Icarus Verilog
$end
$timescale
	1ps
$end
$scope module tb_uart_receiver $end
$var wire 1 ! valid_data $end
$var wire 8 " data [7:0] $end
$var reg 1 # baud_rate_signal $end
$var reg 1 $ clk $end
$var reg 10 % in_data [9:0] $end
$var reg 1 & rst $end
$var reg 1 ' uart_rx $end
$var integer 32 ( i [31:0] $end
$scope module u_uart_receiver $end
$var wire 1 # baud_rate_signal $end
$var wire 1 $ clk $end
$var wire 1 & rst $end
$var wire 1 ' uart_rx $end
$var reg 4 ) bit_counter [3:0] $end
$var reg 8 * d [7:0] $end
$var reg 8 + data [7:0] $end
$var reg 4 , next_bit_counter [3:0] $end
$var reg 1 - next_state $end
$var reg 1 . state $end
$var reg 1 / stop_bit $end
$var reg 1 ! valid_data $end
$var reg 1 0 valid_data_local $end
$upscope $end
$upscope $end
$enddefinitions $end
#0
$dumpvars
00
x/
0.
0-
b0 ,
bx +
b0 *
b0 )
bx (
0'
1&
b1010010110 %
0$
0#
bx "
x!
$end
#5000
0!
b0 "
b0 +
1$
#10000
0$
#15000
1$
#20000
0$
#25000
1$
#30000
0$
#35000
1$
#40000
0$
#45000
1$
#50000
b0 (
0$
0&
#55000
1$
#60000
1-
b1 (
0$
1#
#65000
b1 ,
1.
1$
#70000
b0 ,
0$
0#
#75000
1$
#80000
b1 ,
b1 *
b10 (
1'
0$
1#
#85000
b10 ,
b11 *
b1 "
b1 +
b1 )
1$
#90000
b1 ,
0$
0#
#95000
b11 "
b11 +
1$
#100000
b10 ,
b11 (
0$
1#
#105000
b11 ,
b111 *
b10 )
1$
#110000
b10 ,
0$
0#
#115000
b111 "
b111 +
1$
#120000
b11 ,
b11 *
b100 (
0'
0$
1#
#125000
b100 ,
b11 "
b11 +
b11 )
1$
#130000
b11 ,
0$
0#
#135000
1$
#140000
b100 ,
b1011 *
b101 (
1'
0$
1#
#145000
b101 ,
b11011 *
b1011 "
b1011 +
b100 )
1$
#150000
b100 ,
0$
0#
#155000
b11011 "
b11011 +
1$
#160000
b101 ,
b1011 *
b110 (
0'
0$
1#
#165000
b110 ,
b1011 "
b1011 +
b101 )
1$
#170000
b101 ,
0$
0#
#175000
1$
#180000
b110 ,
b111 (
0$
1#
#185000
b111 ,
b110 )
1$
#190000
b110 ,
0$
0#
#195000
1$
#200000
b111 ,
b1001011 *
b1000 (
1'
0$
1#
#205000
b1000 ,
b11001011 *
b1001011 "
b1001011 +
b111 )
1$
#210000
b111 ,
0$
0#
#215000
b11001011 "
b11001011 +
1$
#220000
b1000 ,
b1001011 *
b1001 (
0'
0$
1#
#225000
0-
b0 ,
0/
b1001011 "
b1001011 +
b1000 )
1$
#230000
1-
b1000 ,
0$
0#
#235000
1$
#240000
0-
b0 ,
10
1/
b1010 (
1'
0$
1#
